XStatic_Hogan-2.0.0.3-py3.6-nspkg.pth
xstatic/pkg/hogan/__init__.py
xstatic/pkg/hogan/data/hogan.js
XStatic_Hogan-2.0.0.3.dist-info/METADATA
XStatic_Hogan-2.0.0.3.dist-info/WHEEL
XStatic_Hogan-2.0.0.3.dist-info/namespace_packages.txt
XStatic_Hogan-2.0.0.3.dist-info/top_level.txt
XStatic_Hogan-2.0.0.3.dist-info/RECORD
