Metadata-Version: 2.1
Name: XStatic-Hogan
Version: 2.0.0.3
Summary: Hogan 2.0.0 (XStatic packaging standard)
Home-page: http://twitter.github.io/hogan.js/
Maintainer: Radomir Dopieralski
Maintainer-email: openstack@sheep.art.pl
License: (same as Hogan)
Keywords: hogan xstatic
Platform: any
